vcf2fhir_test_upgrade/__init__.py
vcf2fhir_test_upgrade/common.py
vcf2fhir_test_upgrade/converter.py
vcf2fhir_test_upgrade/fhir_helper.py
vcf2fhir_test_upgrade/gene_ref_seq.py
vcf2fhir_test_upgrade/json_generator.py
vcf2fhir_test_upgrade/test/__init__.py
vcf2fhir_test_upgrade/test/test_integration.py
vcf2fhir_test_upgrade/test/test_unit.py
vcf2fhir_test_upgrade_test_upgrade-0.0.17.dist-info/LICENSE
vcf2fhir_test_upgrade_test_upgrade-0.0.17.dist-info/METADATA
vcf2fhir_test_upgrade_test_upgrade-0.0.17.dist-info/WHEEL
vcf2fhir_test_upgrade_test_upgrade-0.0.17.dist-info/top_level.txt
vcf2fhir_test_upgrade_test_upgrade-0.0.17.dist-info/RECORD
